pySdk/__init__.py
pySdk/accessToken.py
pySdk/idToken.py
pySdk/renewToken.py
pySdk-0.4.dist-info/LICENSE
pySdk-0.4.dist-info/METADATA
pySdk-0.4.dist-info/WHEEL
pySdk-0.4.dist-info/top_level.txt
pySdk-0.4.dist-info/RECORD
