Metadata-Version: 2.1
Name: pySdk
Version: 0.4
Summary: secuuth  SDK for python scripts
Home-page: https://github.com/akum304/pySdk.git
Author: secuuth
Author-email: amitoshkumar10@gmail.com
License: UNKNOWN
Platform: UNKNOWN
Classifier: Programming Language :: Python :: 3
Classifier: License :: OSI Approved :: MIT License
Classifier: Operating System :: OS Independent
License-File: LICENSE
